netrohomeapi/__init__.py
netrohomeapi/models.py
netrohomeapi/netrohomeapi.py
netrohomeapi-0.2.1.dist-info/LICENSE
netrohomeapi-0.2.1.dist-info/METADATA
netrohomeapi-0.2.1.dist-info/WHEEL
netrohomeapi-0.2.1.dist-info/top_level.txt
netrohomeapi-0.2.1.dist-info/RECORD
