Metadata-Version: 2.1
Name: netrohomeapi
Version: 0.2.1
Summary: Python wrapper for NetroHome API
Home-page: https://github.com/GeorgeBark/netrohomeapi
Download-URL: https://github.com/GeorgeBark/netrohomeapi/archive/refs/tags/v0.1.2.tar.gz
Author: George Bark
Author-email: georgebark2000@gmail.com
License: MIT
Classifier: Development Status :: 4 - Beta
Classifier: Intended Audience :: Developers
Classifier: Topic :: Software Development :: Build Tools
Classifier: License :: OSI Approved :: MIT License
Classifier: Programming Language :: Python :: 3.11
License-File: LICENSE
Requires-Dist: aiohttp
Requires-Dist: pydantic
